[{"Unnamed: 0":1699,"author":"Boucquet victor","life":" ('1619-1677). ","title":"le porte \u00e9tendard d'une compagnie d'archers","width":null,"height":null,"wall":"N","position":"VI tr E","image_path":null},{"Unnamed: 0":1721,"author":"Champaigne philippe de","life":" 1602-1671 - ","title":"le repas chez simon le pharisien","width":399.0,"height":292.0,"wall":"S","position":"VI tr E","image_path":"data\/images_paintings\/1721.jpg"},{"Unnamed: 0":1749,"author":"Dyck anthonis van","life":" (1599-1641). ","title":"saint s\u00e9bastien secouru par les anges","width":145.0,"height":198.0,"wall":"N","position":"VI tr E","image_path":"data\/images_paintings\/1749.jpg"},{"Unnamed: 0":1750,"author":"Dyck anthonis van","life":" (1599-1641). ","title":"v\u00e9nus demandant \u00e0 vulcain des armes pour en\u00e9e","width":null,"height":null,"wall":"N","position":"VI tr E","image_path":null},{"Unnamed: 0":1752,"author":"Dyck anthonis van","life":" (1599-1641). ","title":"portrait en buste de fran\u00e7ois de moncade","width":null,"height":null,"wall":"S","position":"VI tr E","image_path":null},{"Unnamed: 0":1756,"author":"Dyck anthonis van","life":" (1599-1641). ","title":"le gentilhomme \u00e0 l'\u00e9p\u00e9e ' ","width":92.0,"height":113.7,"wall":"S","position":"VI tr E","image_path":"data\/images_paintings\/1756.jpg"},{"Unnamed: 0":1762,"author":"Dyck anthonis van","life":" (1599-1641). ","title":"son portrait par lui m\u00eame","width":null,"height":null,"wall":"S","position":"VI tr E","image_path":"data\/images_paintings\/1762.jpg"},{"Unnamed: 0":1764,"author":"Dyck anthonis van","life":" (1599-1641). ","title":"portraits dits \u00e0 tort de jean crusset richardot pr\u00e9sident du conseil priv\u00e9 des pays bas et de son fils peint par van dyck dans sa jeunesse ","width":null,"height":null,"wall":"S","position":"VI tr E","image_path":null},{"Unnamed: 0":1779,"author":"Jordaens jacob","life":" (1593-1678). ","title":"les quatre \u00e9vang\u00e9listes","width":118.0,"height":134.0,"wall":"N","position":"VI tr E","image_path":"data\/images_paintings\/1779.jpg"},{"Unnamed: 0":1780,"author":"Jordaens jacob","life":" (1593-1678). ","title":"jupiter enfant nourri par la ch\u00e8vre amalth\u00e9e","width":203.0,"height":147.0,"wall":"S","position":"VI tr E","image_path":"data\/images_paintings\/1780.jpg"},{"Unnamed: 0":1781,"author":"Jordaens jacob","life":" (1593-1678). ","title":"le roi boit","width":204.0,"height":152.0,"wall":"N","position":"VI tr E","image_path":"data\/images_paintings\/1781.jpg"},{"Unnamed: 0":1796,"author":"Meulen adam frans van der","life":" (1632-1690). ","title":"d\u00e9faite de l'arm\u00e9e espagnole pr\u00e8s du canal de bruges ao\u00fbt 1667","width":null,"height":null,"wall":"N","position":"VI tr E","image_path":null},{"Unnamed: 0":1797,"author":"Meulen adam frans van der","life":" (1632-1690). ","title":"passage du rhin 12 juin i6y2't","width":null,"height":null,"wall":"N","position":"VI tr E","image_path":null},{"Unnamed: 0":1800,"author":"Meulen adam frans van der","life":" (1632-1690). ","title":"vue du ch\u00e2teau de vincennes du c\u00f4t\u00e9 du parc d\u00e9part de louis xiv pour la chasse","width":null,"height":null,"wall":"N","position":"VI tr E","image_path":null},{"Unnamed: 0":1806,"author":"Mol peeter van","life":" (1599-1650). ","title":"les appr\u00eats de la mise au tombeau","width":null,"height":null,"wall":"N","position":"VI tr E","image_path":null},{"Unnamed: 0":1814,"author":"Pourbus frans","life":" (1=169 ou 15 70-1622). ","title":"la c\u00e8ne","width":370.0,"height":287.0,"wall":"S","position":"VI tr E","image_path":"data\/images_paintings\/1814.jpg"},{"Unnamed: 0":1815,"author":"Pourbus frans","life":" (1=169 ou 15 70-1622). ","title":"saint fran\u00e7ois d'assise recevant les stigmates","width":162.0,"height":227.0,"wall":"N","position":"VI tr E","image_path":"data\/images_paintings\/1815.jpg"},{"Unnamed: 0":1821,"author":"Rubens petrus paulus","life":" ( 1 =,77-1640). ","title":"la famille de loth quittant sodomc","width":null,"height":null,"wall":"S","position":"VI tr E","image_path":"data\/images_paintings\/1821.jpg"},{"Unnamed: 0":1822,"author":"Rubens petrus paulus","life":" ( 1 =,77-1640). ","title":"le proph\u00e8te elie dans le d\u00e9sert par rubens et ses \u00e9l\u00e8ves","width":null,"height":null,"wall":"N","position":"VI tr E","image_path":null},{"Unnamed: 0":1823,"author":"Rubens petrus paulus","life":" ( 1 =,77-1640). ","title":"l'adoration des mages","width":null,"height":null,"wall":"N","position":"VI tr E","image_path":null},{"Unnamed: 0":1827,"author":"Rubens petrus paulus  i","life":" >77-16401. ","title":"le christ en croix","width":null,"height":null,"wall":"N","position":"VI tr E","image_path":"data\/images_paintings\/1827.jpg"},{"Unnamed: 0":1828,"author":"Rubens petrus paulus  i","life":" >77-16401. ","title":"le triomphe de la religion parrubens et ses\u00e9l\u00e8ves","width":null,"height":null,"wall":"S","position":"VI tr E","image_path":null},{"Unnamed: 0":1829,"author":"Rubens petrus paulus  i","life":" >77-16401. ","title":"thomyris reine des scythes fait plonger la t\u00eate de cyrus dans un vase rempli de sang","width":null,"height":null,"wall":"S","position":"VI tr E","image_path":null},{"Unnamed: 0":1854,"author":"Rubens petrus paulus","life":" (1577-1640). ","title":"portrait du baron henri de vicq ambassadeur des pays bas \u00e0 la cour de france","width":null,"height":null,"wall":"S","position":"VI tr E","image_path":null},{"Unnamed: 0":1855,"author":"Rubens petrus paulus","life":" (1577-1640). ","title":"portrait d'anne d'autriche reine de france faussement d\u00e9sign\u00e9 autrefois sous le nom d'elisabeth de france fille de henri iv","width":null,"height":null,"wall":"N","position":"VI tr E","image_path":"data\/images_paintings\/1855.jpg"},{"Unnamed: 0":1856,"author":"Rubens petrus paulus","life":" (1577-1640). ","title":"portrait d'h\u00e9l\u00e8ne fourment seconde femme de rubens avec son fils fran\u00e7ois et sa fille claire jeanne       ","width":null,"height":null,"wall":"S","position":"VI tr E","image_path":null},{"Unnamed: 0":1857,"author":"Rubens petrus paulus","life":" (1577-1640). ","title":"portrait de suzanne fourment s\u0153ur de la seconde femme de rubens     o","width":null,"height":null,"wall":"S","position":"VI tr E","image_path":null},{"Unnamed: 0":1858,"author":"Rubens petrus paulus","life":" (1577-1640). ","title":"la kermesse","width":null,"height":null,"wall":"S","position":"VI tr E","image_path":"data\/images_paintings\/1858.jpg"},{"Unnamed: 0":1859,"author":"Rubens petrus paulus","life":" (1577-1640). ","title":"tournoi pr\u00e8s des foss\u00e9s d'un ch\u00e2teau o","width":null,"height":null,"wall":"S","position":"VI tr E","image_path":null},{"Unnamed: 0":1860,"author":"Rubens petrus paulus","life":" (1577-1640). ","title":"le paysage \u00e0 l'oiseleur","width":null,"height":null,"wall":"N","position":"VI tr E","image_path":null},{"Unnamed: 0":1878,"author":"Ryckaert david","life":" (1612-1661). ","title":"l'atelier pr\u00e9sum\u00e9 du p\u00e8re de l'artiste david rycka\u00ebrt ii","width":null,"height":null,"wall":"N","position":"VI tr E","image_path":null},{"Unnamed: 0":1880,"author":"Snyders frans","life":" (1579-1657). ","title":"les marchands de poissons attribu\u00e9","width":null,"height":null,"wall":"N","position":"VI tr E","image_path":null},{"Unnamed: 0":1881,"author":"Snyders frans","life":" (1579-1657). ","title":"les chiens dans le garde manger","width":null,"height":null,"wall":"N","position":"VI tr E","image_path":null},{"Unnamed: 0":1887,"author":"Teniers david","life":" (I\u00d4IO-I6QO). ","title":"la f\u00eate de village grand exemplaire","width":null,"height":null,"wall":"N","position":"VI tr E","image_path":null},{"Unnamed: 0":1895,"author":"Teniers david","life":" (I\u00d4IO-I6QO). ","title":"l'archiduc l\u00e9opold \u00e0 la chasse au h\u00e9ron","width":null,"height":null,"wall":"N","position":"VI tr E","image_path":null},{"Unnamed: 0":1916,"author":"Thulden theodor van","life":" ( 1606- probablement 1676). ","title":"portraits d'homme et de femme r\u00e9unis dans un sujet pastoral attribu\u00e9 imitation du \u00abjacob et rachel \u00e0 la fontaine\u00bb par rubens dans la collection de la baronne v g \u00e0 carisruhe","width":null,"height":null,"wall":"N","position":"VI tr E","image_path":null},{"Unnamed: 0":1923,"author":"Vos paul de","life":" (vers 1590-1678). ","title":"le paradis terrestre attribu\u00e9","width":null,"height":null,"wall":"S","position":"VI tr E","image_path":null},{"Unnamed: 0":1924,"author":"Vos paul de","life":" (vers 1590-1678). ","title":"entr\u00e9e des animaux dans l'arche de no\u00e9 attribu\u00e9","width":null,"height":null,"wall":"S","position":"VI tr E","image_path":null},{"Unnamed: 0":1925,"author":"Vos paul de","life":" (vers 1590-1678). ","title":"chasse au sanglier attribu\u00e9","width":null,"height":null,"wall":"N","position":"VI tr E","image_path":null}]